LICENSE
MANIFEST.in
README.rst
setup.py
pyfofa/__init__.py
pyfofa/__version__.py
pyfofa/api.py
pyfofa.egg-info/PKG-INFO
pyfofa.egg-info/SOURCES.txt
pyfofa.egg-info/dependency_links.txt
pyfofa.egg-info/requires.txt
pyfofa.egg-info/top_level.txt