Metadata-Version: 1.2
Name: pyfofa
Version: 1.0.0
Summary: Python3 library for FOFA (https://fofa.so)
Home-page: https://github.com/h4rdy/fofa-sdk
Author: H4rdy
Author-email: with.h4rdy@gmail.com
License: LICENSE.txt
Platform: UNKNOWN
Requires-Python: >=3.6.0
